Metadata-Version: 1.0
Name: sub-distributions
Version: 0.1
Summary: Gaussian and Binomial distributions
Home-page: UNKNOWN
Author: Subham Kumar Gupta
Author-email: guptasubham175@gmail.com
License: UNKNOWN
Platform: UNKNOWN
